verifact/__init__.py
verifact/error.py
verifact/invoice.py
verifact/metadata.py
verifact/settings.py
verifact/format_export/__init__.py
verifact/format_export/excel_export.py
verifact/format_import/__init__.py
verifact/format_import/base_import.py
verifact/format_import/cador_csv_import.py
verifact/format_import/cador_xlsx_import.py
verifact/format_import/fec_import.py
verifact/format_invoice/__init__.py
verifact/format_invoice/serial.py
verifact/format_invoice/serialManager.py
verifact/gui/__init__.py
verifact/gui/about.py
verifact/gui/app.py
verifact/gui/main.py
verifact/gui/menu.py
verifact/gui/progressbar.py
verifact/gui/settings.py
verifact/gui/update.py
verifacturation-1.4.6.dist-info/License
verifacturation-1.4.6.dist-info/METADATA
verifacturation-1.4.6.dist-info/WHEEL
verifacturation-1.4.6.dist-info/entry_points.txt
verifacturation-1.4.6.dist-info/top_level.txt
verifacturation-1.4.6.dist-info/RECORD
