Metadata-Version: 2.2
Name: VeriFacturation
Version: 1.4.6
Summary: Logiciel de vérification de la numérotation des factures.
Home-page: https://github.com/Atem83/VeriFacturation
Author: Michaël AUGUSTE
License: MIT
Classifier: Operating System :: OS Independent
Classifier: Programming Language :: Python :: 3.6
Classifier: License :: OSI Approved :: MIT License
Requires-Python: >=3.6
License-File: License
Requires-Dist: polars
Requires-Dist: PySide6
Requires-Dist: openpyxl
Requires-Dist: xlsxwriter
